Workbook
Name IQ_CH: 110000
Name IQ_CQ: 5000
Name IQ_CY: 10000
Name IQ_DAILY: 500000
Name IQ_FH: 100000
Name IQ_FQ: 500
Name IQ_FY: 1000
Name IQ_LTM: 2000
Name IQ_MONTH: 15000
Name IQ_NTM: 6000
Name IQ_WEEK: 50000
Name IQ_YTD: 3000

Sheet Bilateral
A1: country_name | B1: country_code | C1: year | D1: income_group | E1: DT.DOD.BLAT.CD_total | F1: DT.DOD.BLAT.CD_pc | G1: DT.DOD.BLAT.CD_nonpc
A2: Afghanistan | B2: AFG | C2: 2006 | D2: LIC | E2: 2.6602583e+08 | F2: 132286000 | G2: 1.3373983e+08
A3: Afghanistan | B3: AFG | C3: 2007 | D3: LIC | E3: 1.083038e+09 | F3: 941023000 | G3: 1.4201502e+08
A4: Afghanistan | B4: AFG | C4: 2008 | D4: LIC | E4: 1090606093 | F4: 980025000 | G4: 110581093
A5: Afghanistan | B5: AFG | C5: 2009 | D5: LIC | E5: 1.0891679e+09 | F5: 9.7909853e+08 | G5: 1.1006941e+08
A6: Afghanistan | B6: AFG | C6: 2010 | D6: LIC | E6: 9.5947619e+08 | F6: 8.4911922e+08 | G6: 1.1035696e+08
A7: Afghanistan | B7: AFG | C7: 2011 | D7: LIC | E7: 9.5957406e+08 | F7: 8.4911922e+08 | G7: 1.1045484e+08
A8: Afghanistan | B8: AFG | C8: 2012 | D8: LIC | E8: 9.5944635e+08 | F8: 8.4911959e+08 | G8: 1.1032676e+08
A9: Afghanistan | B9: AFG | C9: 2013 | D9: LIC | E9: 9.5940863e+08 | F9: 8.4911959e+08 | G9: 1.1028903e+08
A10: Afghanistan | B10: AFG | C10: 2014 | D10: LIC | E10: 9.3449455e+08 | F10: 849119000 | G10: 85375546
A11: Afghanistan | B11: AFG | C11: 2015 | D11: LIC | E11: 9.6018425e+08 | F11: 849119000 | G11: 1.1106525e+08
A12: Afghanistan | B12: AFG | C12: 2016 | D12: LIC | E12: 958261439 | F12: 850489330 | G12: 107772109
A13: Afghanistan | B13: AFG | C13: 2017 | D13: LIC | E13: 9.5861563e+08 | F13: 850678090 | G13: 1.0793754e+08
... A5695: Zimbabwe | B5695: ZWE | C5695: 2024 | D5695: LIC | E5695: 3.0493184e+09 | F5695: 9.4656822e+08 | G5695: 2.1027502e+09

Sheet Multilateral
A1: country_name | B1: country_code | C1: year | D1: income_group | E1: DT.DOD.MLAT.CD_total | F1: DT.DOD.MLAT.CD_pcs | G1: DT.DOD.MLAT.CD_nonpcs
A2: Afghanistan | B2: AFG | C2: 2006 | D2: LIC | E2: 6.5359973e+08 | F2: 6.5359973e+08 | G2: 0
A3: Afghanistan | B3: AFG | C3: 2007 | D3: LIC | E3: 8.1917548e+08 | F3: 8.1917548e+08 | G3: 0
A4: Afghanistan | B4: AFG | C4: 2008 | D4: LIC | E4: 903502910 | F4: 903502910 | G4: 0
A5: Afghanistan | B5: AFG | C5: 2009 | D5: LIC | E5: 1016543849 | F5: 1016543849 | G5: 0
A6: Afghanistan | B6: AFG | C6: 2010 | D6: LIC | E6: 1.016071e+09 | F6: 1.016071e+09 | G6: 0
A7: Afghanistan | B7: AFG | C7: 2011 | D7: LIC | E7: 1072890186 | F7: 1072890186 | G7: 0
A8: Afghanistan | B8: AFG | C8: 2012 | D8: LIC | E8: 1.1203397e+09 | F8: 1.1203397e+09 | G8: 0
A9: Afghanistan | B9: AFG | C9: 2013 | D9: LIC | E9: 1.1468229e+09 | F9: 1.1468229e+09 | G9: 0
A10: Afghanistan | B10: AFG | C10: 2014 | D10: LIC | E10: 1.0864573e+09 | F10: 1.0864573e+09 | G10: 0
A11: Afghanistan | B11: AFG | C11: 2015 | D11: LIC | E11: 1.0297705e+09 | F11: 1.0297705e+09 | G11: 0
A12: Afghanistan | B12: AFG | C12: 2016 | D12: LIC | E12: 9.9124453e+08 | F12: 9.9124453e+08 | G12: 0
A13: Afghanistan | B13: AFG | C13: 2017 | D13: LIC | E13: 1.022951e+09 | F13: 1.022951e+09 | G13: 0
... A5670: Zimbabwe | B5670: ZWE | C5670: 2024 | D5670: LIC | E5670: 1.7968145e+09 | F5670: 1.3885098e+09 | G5670: 4.0830474e+08

Sheet Bonds
A1: country_name | B1: country_code | C1: year | D1: income_group | E1: bonds_value
A2: Albania | B2: ALB | C2: 2008 | D2: MIC | E2: 79326900
A3: Albania | B3: ALB | C3: 2009 | D3: MIC | E3: 82114200
A4: Albania | B4: ALB | C4: 2010 | D4: MIC | E4: 477023400
A5: Albania | B5: ALB | C5: 2011 | D5: MIC | E5: 556377000
A6: Albania | B6: ALB | C6: 2012 | D6: MIC | E6: 567342000
A7: Albania | B7: ALB | C7: 2013 | D7: MIC | E7: 593013000
A8: Albania | B8: ALB | C8: 2014 | D8: MIC | E8: 522063000
A9: Albania | B9: ALB | C9: 2015 | D9: MIC | E9: 631446000
A10: Albania | B10: ALB | C10: 2016 | D10: MIC | E10: 611378000
A11: Albania | B11: ALB | C11: 2017 | D11: MIC | E11: 695594000
A12: Albania | B12: ALB | C12: 2018 | D12: MIC | E12: 717571500
A13: Albania | B13: ALB | C13: 2019 | D13: MIC | E13: 642247780
... A2435: Zimbabwe | B2435: ZWE | C2435: 2024 | D2435: LIC | E2435: 25972.5

Sheet Commercial Banks
A1: country_name | B1: country_code | C1: year | D1: income_group | E1: commbanks_value
A2: Albania | B2: ALB | C2: 1995 | D2: MIC | E2: 0
A3: Albania | B3: ALB | C3: 2006 | D3: MIC | E3: 0
A4: Albania | B4: ALB | C4: 2007 | D4: MIC | E4: 116295.9
A5: Albania | B5: ALB | C5: 2008 | D5: MIC | E5: 3.2676698e+08
A6: Albania | B6: ALB | C6: 2009 | D6: MIC | E6: 6.4779604e+08
A7: Albania | B7: ALB | C7: 2010 | D7: MIC | E7: 5.4799967e+08
A8: Albania | B8: ALB | C8: 2011 | D8: MIC | E8: 4.8545446e+08
A9: Albania | B9: ALB | C9: 2012 | D9: MIC | E9: 4.2964678e+08
A10: Albania | B10: ALB | C10: 2013 | D10: MIC | E10: 4.5687928e+08
A11: Albania | B11: ALB | C11: 2014 | D11: MIC | E11: 3.8459896e+08
A12: Albania | B12: ALB | C12: 2015 | D12: MIC | E12: 6.1721125e+08
A13: Albania | B13: ALB | C13: 2016 | D13: MIC | E13: 6.0842336e+08
... A4321: Zimbabwe | B4321: ZWE | C4321: 2024 | D4321: LIC | E4321: 360829718

Sheet Other Private
A1: country_name | B1: country_code | C1: year | D1: income_group | E1: otherprivate_value
A2: Afghanistan | B2: AFG | C2: 2006 | D2: LIC | E2: 397000
A3: Afghanistan | B3: AFG | C3: 2007 | D3: LIC | E3: 397000
A4: Afghanistan | B4: AFG | C4: 2008 | D4: LIC | E4: 397000
A5: Afghanistan | B5: AFG | C5: 2009 | D5: LIC | E5: 397000
A6: Afghanistan | B6: AFG | C6: 2010 | D6: LIC | E6: 0
A7: Albania | B7: ALB | C7: 1991 | D7: MIC | E7: 64133284
A8: Albania | B8: ALB | C8: 1992 | D8: MIC | E8: 63309616
A9: Albania | B9: ALB | C9: 1993 | D9: MIC | E9: 23068686
A10: Albania | B10: ALB | C10: 1994 | D10: MIC | E10: 19201523
A11: Albania | B11: ALB | C11: 1995 | D11: MIC | E11: 24969546
A12: Albania | B12: ALB | C12: 1996 | D12: MIC | E12: 29224260
A13: Albania | B13: ALB | C13: 1997 | D13: MIC | E13: 27308968
... A4329: Zimbabwe | B4329: ZWE | C4329: 2024 | D4329: LIC | E4329: 1.0678275e+08

Sheet IMF Credit
A1: country_name | B1: country_code | C1: year | D1: income_group | E1: imf_value
A2: Afghanistan | B2: AFG | C2: 2006 | D2: LIC | E2: 40171993
A3: Afghanistan | B3: AFG | C3: 2007 | D3: LIC | E3: 98770366
A4: Afghanistan | B4: AFG | C4: 2008 | D4: LIC | E4: 1.310816e+08
A5: Afghanistan | B5: AFG | C5: 2009 | D5: LIC | E5: 3.5275262e+08
A6: Afghanistan | B6: AFG | C6: 2010 | D6: LIC | E6: 3.5522989e+08
A7: Afghanistan | B7: AFG | C7: 2011 | D7: LIC | E7: 3.7255517e+08
A8: Afghanistan | B8: AFG | C8: 2012 | D8: LIC | E8: 3.8763312e+08
A9: Afghanistan | B9: AFG | C9: 2013 | D9: LIC | E9: 3.7564317e+08
A10: Afghanistan | B10: AFG | C10: 2014 | D10: LIC | E10: 3.3483912e+08
A11: Afghanistan | B11: AFG | C11: 2015 | D11: LIC | E11: 3.0016171e+08
A12: Afghanistan | B12: AFG | C12: 2016 | D12: LIC | E12: 2.7698477e+08
A13: Afghanistan | B13: AFG | C13: 2017 | D13: LIC | E13: 2.8485391e+08
... A5288: Zimbabwe | B5288: ZWE | C5288: 2024 | D5288: LIC | E5288: 1.325023e+09

Sheet Total PPG
A1: country_name | B1: country_code | C1: year | D1: income_group | E1: total_ppg_value
A2: Afghanistan | B2: AFG | C2: 2006 | D2: LIC | E2: 9.2002256e+08
A3: Afghanistan | B3: AFG | C3: 2007 | D3: LIC | E3: 1.9026105e+09
A4: Afghanistan | B4: AFG | C4: 2008 | D4: LIC | E4: 1994506003
A5: Afghanistan | B5: AFG | C5: 2009 | D5: LIC | E5: 2.1061088e+09
A6: Afghanistan | B6: AFG | C6: 2010 | D6: LIC | E6: 1.9755472e+09
A7: Afghanistan | B7: AFG | C7: 2011 | D7: LIC | E7: 2.0324642e+09
A8: Afghanistan | B8: AFG | C8: 2012 | D8: LIC | E8: 2.079786e+09
A9: Afghanistan | B9: AFG | C9: 2013 | D9: LIC | E9: 2.1062315e+09
A10: Afghanistan | B10: AFG | C10: 2014 | D10: LIC | E10: 2.0209519e+09
A11: Afghanistan | B11: AFG | C11: 2015 | D11: LIC | E11: 1.9899548e+09
A12: Afghanistan | B12: AFG | C12: 2016 | D12: LIC | E12: 1.949506e+09
A13: Afghanistan | B13: AFG | C13: 2017 | D13: LIC | E13: 1.9815666e+09
... A5706: Zimbabwe | B5706: ZWE | C5706: 2024 | D5706: LIC | E5706: 5.3137714e+09

Sheet Cross-check
A1: country_name | B1: year | C1: income_group | D1: our_sum | E1: total_ppg_value | F1: diff_pct
A2: Afghanistan | B2: 2006 | C2: LIC | D2: 9.2002256e+08 | E2: 9.2002256e+08 | F2: 0
A3: Afghanistan | B3: 2007 | C3: LIC | D3: 1.9026105e+09 | E3: 1.9026105e+09 | F3: 0
A4: Afghanistan | B4: 2008 | C4: LIC | D4: 1994506003 | E4: 1994506003 | F4: 0
A5: Afghanistan | B5: 2009 | C5: LIC | D5: 2.1061088e+09 | E5: 2.1061088e+09 | F5: 0
A6: Afghanistan | B6: 2010 | C6: LIC | D6: 1.9755472e+09 | E6: 1.9755472e+09 | F6: 0
A7: Afghanistan | B7: 2011 | C7: LIC | D7: 2.0324642e+09 | E7: 2.0324642e+09 | F7: 0
A8: Afghanistan | B8: 2012 | C8: LIC | D8: 2.079786e+09 | E8: 2.079786e+09 | F8: 0
A9: Afghanistan | B9: 2013 | C9: LIC | D9: 2.1062315e+09 | E9: 2.1062315e+09 | F9: 0
A10: Afghanistan | B10: 2014 | C10: LIC | D10: 2.0209519e+09 | E10: 2.0209519e+09 | F10: 0
A11: Afghanistan | B11: 2015 | C11: LIC | D11: 1.9899548e+09 | E11: 1.9899548e+09 | F11: 0
A12: Afghanistan | B12: 2016 | C12: LIC | D12: 1.949506e+09 | E12: 1.949506e+09 | F12: 0
A13: Afghanistan | B13: 2017 | C13: LIC | D13: 1.9815666e+09 | E13: 1.9815666e+09 | F13: 0
... A5695: Zimbabwe | B5695: 2024 | C5695: LIC | D5695: 5.3137714e+09 | E5695: 5.3137714e+09 | F5695: 0

Sheet Chart - All (sum)
A1: year | B1: Bilateral_PC | C1: Bilateral_NonPC | D1: Multilateral_PCS | E1: Multilateral_NonPCS | F1: Bonds | G1: Commercial_Banks | H1: Other_Private | I1: IMF
A2: 1970 | B2: 18.791338 | C2: 4.8552824 | D2: 7.2555783 | E2: 0.15255734 | F2: 1.4767602 | G2: 2.9910425 | H2: 5.8145014 | I2: 0.72672
A3: 1971 | B3: 22.827276 | C3: 5.1257039 | D3: 8.347847 | E3: 0.18934793 | F3: 1.6381434 | G3: 3.8920042 | H3: 6.6259609 | I3: 0.80111197
A4: 1972 | B4: 24.917235 | C4: 5.5459473 | D4: 9.8962692 | E4: 0.14269836 | F4: 1.7871984 | G4: 5.9866127 | H4: 7.6648257 | I4: 1.0114164
A5: 1973 | B5: 28.439587 | C5: 6.3266531 | D5: 11.768033 | E5: 0.19078074 | F5: 2.0230329 | G5: 10.690513 | H5: 9.3841588 | I5: 1.0954404
A6: 1974 | B6: 32.334548 | C6: 7.6916116 | D6: 14.1147 | E6: 0.32003322 | F6: 2.1937551 | G6: 16.793496 | H6: 11.232491 | I6: 2.1454577
A7: 1975 | B7: 34.693772 | C7: 11.439897 | D7: 17.141265 | E7: 0.47008466 | F7: 2.2468047 | G7: 24.909794 | H7: 13.461384 | I7: 3.4232313
A8: 1976 | B8: 37.87251 | C8: 13.730874 | D8: 20.492409 | E8: 0.63128005 | F8: 3.2931576 | G8: 34.7403 | H8: 16.678616 | I8: 5.3787791
A9: 1977 | B9: 44.488166 | C9: 16.510153 | D9: 24.282066 | E9: 2.02744 | F9: 5.7287906 | G9: 44.897609 | H9: 22.547917 | I9: 5.5888486
A10: 1978 | B10: 52.646201 | C10: 19.748554 | D10: 28.545947 | E10: 2.8898573 | F10: 8.8889649 | G10: 59.982255 | H10: 29.361261 | I10: 6.6732772
A11: 1979 | B11: 57.305594 | C11: 21.897242 | D11: 33.848698 | E11: 3.2097026 | F11: 9.6954658 | G11: 78.259951 | H11: 33.403787 | I11: 8.383357
A12: 1980 | B12: 66.843984 | C12: 27.061111 | D12: 40.700967 | E12: 3.5040921 | F12: 10.126539 | G12: 94.073153 | H12: 40.180218 | I12: 11.054662
A13: 1981 | B13: 70.655336 | C13: 33.168705 | D13: 47.897657 | E13: 3.7473526 | F13: 10.623011 | G13: 110.62618 | H13: 43.733242 | I13: 16.067472
... A56: 2024 | B56: 241.38819 | C56: 234.70011 | D56: 899.45703 | E56: 89.135296 | F56: 1637.2307 | G56: 368.13225 | H56: 91.810089 | I56: 371.90707

Sheet Chart - LIC (sum)
A1: year | B1: Bilateral_PC | C1: Bilateral_NonPC | D1: Multilateral_PCS | E1: Multilateral_NonPCS | F1: Bonds | G1: Commercial_Banks | H1: Other_Private | I1: IMF
A2: 1970 | B2: 2.4321967 | C2: 0.8906786 | D2: 0.79679059 | E2: 0.051543759 | F2: 0.33833256 | G2: 0.15498869 | H2: 1.0560358 | I2: 0.13375
A3: 1971 | B3: 3.4898264 | C3: 1.1104103 | D3: 0.95373603 | E3: 0.071635728 | F3: 0.33909661 | G3: 0.30214166 | H3: 1.2102309 | I3: 0.12192984
A4: 1972 | B4: 3.7099991 | C4: 1.418884 | D4: 1.1850105 | E4: 0.097744656 | F4: 0.29922515 | G4: 0.47556274 | H4: 1.3909216 | I4: 0.21516378
A5: 1973 | B5: 4.4313281 | C5: 2.0318668 | D5: 1.5554843 | E5: 0.13381442 | F5: 0.34641103 | G5: 0.96098459 | H5: 1.5900896 | I5: 0.28758063
A6: 1974 | B6: 5.7308649 | C6: 2.7114583 | D6: 2.0346729 | E6: 0.2467284 | F6: 0.35955835 | G6: 1.3303124 | H6: 2.0109222 | I6: 0.61236028
A7: 1975 | B7: 6.2919954 | C7: 3.3530525 | D7: 2.6921357 | E7: 0.36599506 | F7: 0.34040535 | G7: 1.5310167 | H7: 2.7470758 | I7: 0.97849322
A8: 1976 | B8: 6.5299966 | C8: 4.0826048 | D8: 3.4608826 | E8: 0.4849806 | F8: 0.28738542 | G8: 1.7107447 | H8: 3.416645 | I8: 1.3895844
A9: 1977 | B9: 8.4033741 | C9: 4.9701537 | D9: 4.5062952 | E9: 0.60340881 | F9: 0.31391463 | G9: 2.3814872 | H9: 4.6687631 | I9: 1.4875549
A10: 1978 | B10: 9.5135375 | C10: 6.1109078 | D10: 5.7538587 | E10: 0.80883149 | F10: 0.54590829 | G10: 3.0525317 | H10: 6.1880958 | I10: 2.180423
A11: 1979 | B11: 10.812394 | C11: 7.5911128 | D11: 7.1004849 | E11: 0.98828669 | F11: 0.63299481 | G11: 3.5528614 | H11: 7.2027652 | I11: 3.0096223
A12: 1980 | B12: 13.112577 | C12: 9.0874341 | D12: 8.8531468 | E12: 1.2119313 | F12: 0.72453974 | G12: 5.0730257 | H12: 8.0147485 | I12: 3.7028009
A13: 1981 | B13: 14.153041 | C13: 11.379248 | D13: 10.693409 | E13: 1.3492421 | F13: 0.49495888 | G13: 6.7452977 | H13: 7.9124458 | I13: 5.115768
... A56: 2024 | B56: 62.427789 | C56: 104.42896 | D56: 244.3189 | E56: 15.945607 | F56: 54.735858 | G56: 47.530387 | H56: 7.7777487 | I56: 67.648707

Sheet Chart - MIC (sum)
A1: year | B1: Bilateral_PC | C1: Bilateral_NonPC | D1: Multilateral_PCS | E1: Multilateral_NonPCS | F1: Bonds | G1: Commercial_Banks | H1: Other_Private | I1: IMF
A2: 1970 | B2: 16.359141 | C2: 3.9646038 | D2: 6.4587877 | E2: 0.10101358 | F2: 1.1384276 | G2: 2.8360538 | H2: 4.7584656 | I2: 0.59297
A3: 1971 | B3: 19.33745 | C3: 4.0152936 | D3: 7.3941109 | E3: 0.1177122 | F3: 1.2990468 | G3: 3.5898625 | H3: 5.41573 | I3: 0.67918213
A4: 1972 | B4: 21.207236 | C4: 4.1270633 | D4: 8.7112587 | E4: 0.044953699 | F4: 1.4879733 | G4: 5.51105 | H4: 6.2739041 | I4: 0.79625267
A5: 1973 | B5: 24.008259 | C5: 4.2947863 | D5: 10.212549 | E5: 0.056966318 | F5: 1.6766218 | G5: 9.7295288 | H5: 7.7940692 | I5: 0.80785978
A6: 1974 | B6: 26.603683 | C6: 4.9801533 | D6: 12.080028 | E6: 0.073304817 | F6: 1.8341968 | G6: 15.463183 | H6: 9.2215684 | I6: 1.5330974
A7: 1975 | B7: 28.401777 | C7: 8.086845 | D7: 14.44913 | E7: 0.1040896 | F7: 1.9063994 | G7: 23.378777 | H7: 10.714309 | I7: 2.444738
A8: 1976 | B8: 31.342513 | C8: 9.6482696 | D8: 17.031527 | E8: 0.14629945 | F8: 3.0057721 | G8: 33.029556 | H8: 13.261971 | I8: 3.9891948
A9: 1977 | B9: 36.084792 | C9: 11.54 | D9: 19.77577 | E9: 1.4240312 | F9: 5.414876 | G9: 42.516122 | H9: 17.879154 | I9: 4.1012937
A10: 1978 | B10: 43.132664 | C10: 13.637646 | D10: 22.792088 | E10: 2.0810259 | F10: 8.3430566 | G10: 56.929723 | H10: 23.173165 | I10: 4.4928542
A11: 1979 | B11: 46.4932 | C11: 14.306129 | D11: 26.748213 | E11: 2.2214159 | F11: 9.062471 | G11: 74.70709 | H11: 26.201022 | I11: 5.3737347
A12: 1980 | B12: 53.731407 | C12: 17.973677 | D12: 31.84782 | E12: 2.2921608 | F12: 9.4019992 | G12: 89.000127 | H12: 32.16547 | I12: 7.3518614
A13: 1981 | B13: 56.502294 | C13: 21.789457 | D13: 37.204248 | E13: 2.3981106 | F13: 10.128052 | G13: 103.88088 | H13: 35.820796 | I13: 10.951704
... A56: 2024 | B56: 178.9604 | C56: 130.27115 | D56: 655.13813 | E56: 73.189689 | F56: 1582.4949 | G56: 320.60186 | H56: 84.032341 | I56: 304.25836

Sheet Chart - All (median %)
A1: year | B1: pct_Bilateral_PC | C1: pct_Bilateral_NonPC | D1: pct_Multilateral_PCS | E1: pct_Multilateral_NonPCS | F1: pct_Bonds | G1: pct_Commercial_Banks | H1: pct_Other_Private | I1: pct_IMF
A2: 1970 | B2: 39.739953 | C2: 3.0545895 | D2: 12.624066 | E2: 0 | F2: 0.041702466 | G2: 0.16846586 | H2: 9.6341224 | I2: 0
A3: 1971 | B3: 40.406569 | C3: 3.2382064 | D3: 15.502897 | E3: 0 | F3: 0.029938544 | G3: 0.20069962 | H3: 9.9479794 | I3: 0
A4: 1972 | B4: 38.598868 | C4: 2.9877335 | D4: 16.722112 | E4: 0 | F4: 0.042303595 | G4: 0.49170602 | H4: 9.4167737 | I4: 0
A5: 1973 | B5: 39.69913 | C5: 3.3731165 | D5: 16.7735 | E5: 0 | F5: 0.069052831 | G5: 1.0687892 | H5: 7.6299938 | I5: 0
A6: 1974 | B6: 36.231994 | C6: 2.9897877 | D6: 16.059038 | E6: 0 | F6: 0.039911144 | G6: 1.1641065 | H6: 9.042597 | I6: 0
A7: 1975 | B7: 30.477436 | C7: 6.1335214 | D7: 17.293865 | E7: 0 | F7: 0.013055718 | G7: 0.97531641 | H7: 8.7792033 | I7: 0
A8: 1976 | B8: 26.822595 | C8: 7.4007967 | D8: 18.699294 | E8: 0.01568422 | F8: 0.0059695877 | G8: 1.3222413 | H8: 7.418942 | I8: 3.4226348
A9: 1977 | B9: 24.817519 | C9: 10.415551 | D9: 19.51832 | E9: 0.11310272 | F9: 0 | G9: 1.3711907 | H9: 6.8222356 | I9: 2.8258247
A10: 1978 | B10: 24.231985 | C10: 9.1141335 | D10: 18.853912 | E10: 0.29898387 | F10: 0 | G10: 4.3089593 | H10: 7.1070946 | I10: 3.3425333
A11: 1979 | B11: 20.427936 | C11: 10.088392 | D11: 19.021703 | E11: 0.57420206 | F11: 0 | G11: 3.8698246 | H11: 6.4913426 | I11: 4.5968943
A12: 1980 | B12: 19.027249 | C12: 11.400856 | D12: 19.937466 | E12: 0.7024287 | F12: 0 | G12: 7.4274346 | H12: 6.9536022 | I12: 4.9569397
A13: 1981 | B13: 17.278917 | C13: 10.480858 | D13: 21.322117 | E13: 0.83622059 | F13: 0 | G13: 9.1260208 | H13: 7.369707 | I13: 4.8571472
... A56: 2024 | B56: 4.5605958 | C56: 9.6914411 | D56: 36.612086 | E56: 0.52467636 | F56: 5.6562087 | G56: 1.7292032 | H56: 0 | I56: 11.683416

Sheet Chart - LIC (median %)
A1: year | B1: pct_Bilateral_PC | C1: pct_Bilateral_NonPC | D1: pct_Multilateral_PCS | E1: pct_Multilateral_NonPCS | F1: pct_Bonds | G1: pct_Commercial_Banks | H1: pct_Other_Private | I1: pct_IMF
A2: 1970 | B2: 45.658708 | C2: 3.251272 | D2: 9.718637 | E2: 0 | F2: 0 | G2: 0 | H2: 9.789562 | I2: 0
A3: 1971 | B3: 44.141864 | C3: 4.2443129 | D3: 10.83325 | E3: 0 | F3: 0 | G3: 0 | H3: 8.9706429 | I3: 0
A4: 1972 | B4: 39.405158 | C4: 4.9758693 | D4: 15.068458 | E4: 0 | F4: 0 | G4: 0 | H4: 7.6960497 | I4: 0
A5: 1973 | B5: 30.578687 | C5: 5.1044962 | D5: 12.996006 | E5: 0 | F5: 0 | G5: 0.077654206 | H5: 7.6299938 | I5: 0
A6: 1974 | B6: 31.229706 | C6: 5.0073772 | D6: 14.552288 | E6: 0 | F6: 0 | G6: 0.44845302 | H6: 9.2009994 | I6: 0
A7: 1975 | B7: 28.876345 | C7: 7.1529057 | D7: 15.224937 | E7: 0.2806842 | F7: 0 | G7: 0.14332959 | H7: 8.0241921 | I7: 2.2882388
A8: 1976 | B8: 25.565587 | C8: 12.256348 | D8: 18.754925 | E8: 0.46803597 | F8: 0 | G8: 0.22229976 | H8: 6.890248 | I8: 4.4042258
A9: 1977 | B9: 21.339671 | C9: 11.022876 | D9: 19.610208 | E9: 0.47695515 | F9: 0 | G9: 0.2549168 | H9: 7.9252355 | I9: 3.7413066
A10: 1978 | B10: 19.085527 | C10: 10.842735 | D10: 19.749253 | E10: 0.71221658 | F10: 0 | G10: 0.65883195 | H10: 8.5682422 | I10: 4.508254
A11: 1979 | B11: 18.147896 | C11: 13.592922 | D11: 20.717672 | E11: 0.78713005 | F11: 0 | G11: 1.4709424 | H11: 6.4913426 | I11: 5.6147779
A12: 1980 | B12: 16.803068 | C12: 11.966859 | D12: 22.32703 | E12: 0.95605083 | F12: 0 | G12: 2.0838489 | H12: 6.5044917 | I12: 5.9897077
A13: 1981 | B13: 13.778048 | C13: 13.870036 | D13: 24.548865 | E13: 1.0819356 | F13: 0 | G13: 1.7272914 | H13: 6.962448 | I13: 6.362037
... A56: 2024 | B56: 4.5226523 | C56: 18.674166 | D56: 40.089236 | E56: 0.74172504 | F56: 0 | G56: 1.0526253 | H56: 0 | I56: 13.171728

Sheet Chart - LIC (median USD)
A1: year | B1: Bilateral_PC | C1: Bilateral_NonPC | D1: Multilateral_PCS | E1: Multilateral_NonPCS | F1: Bonds | G1: Commercial_Banks | H1: Other_Private | I1: IMF
A2: 1970 | B2: {=MEDIAN(IF(Bilateral!C:C=A2, Bilateral!F:F))} -> 52508739 | C2: {=MEDIAN(IF(Bilateral!C:C=A2,Bilateral!G:G))} -> 2019093.9 | D2: {=MEDIAN(IF(Multilateral!C:C=A2, Multilateral!F:F))} -> 20405000 | E2: {=MEDIAN(IF(Multilateral!C:C=A2, Multilateral!G:G))} -> 0 | F2: {=MEDIAN(IF(Bonds!C:C=A2, Bonds!E:E))} -> 8994000 | G2: {=MEDIAN(IF('Commercial Banks'!C:C=A2, 'Commercial Banks'!E:E))} -> 4898228.8 | H2: {=MEDIAN(IF('Other Private'!C:C=A2, 'Other Private'!E:E))} -> 14089224 | I2: {=MEDIAN(IF('IMF Credit'!C:C=A2, 'IMF Credit'!E:E))} -> 0
A3: 1971 | B3: {=MEDIAN(IF(Bilateral!C:C=A3, Bilateral!F:F))} -> 56041212 | C3: {=MEDIAN(IF(Bilateral!C:C=A3,Bilateral!G:G))} -> 3285000 | D3: {=MEDIAN(IF(Multilateral!C:C=A3, Multilateral!F:F))} -> 27278500 | E3: {=MEDIAN(IF(Multilateral!C:C=A3, Multilateral!G:G))} -> 0 | F3: {=MEDIAN(IF(Bonds!C:C=A3, Bonds!E:E))} -> 7716684.3 | G3: {=MEDIAN(IF('Commercial Banks'!C:C=A3, 'Commercial Banks'!E:E))} -> 11158435 | H3: {=MEDIAN(IF('Other Private'!C:C=A3, 'Other Private'!E:E))} -> 20625081 | I3: {=MEDIAN(IF('IMF Credit'!C:C=A3, 'IMF Credit'!E:E))} -> 0 | K3: use this: External PPG Debt (Median; %)
A4: 1972 | B4: {=MEDIAN(IF(Bilateral!C:C=A4, Bilateral!F:F))} -> 53021838 | C4: {=MEDIAN(IF(Bilateral!C:C=A4,Bilateral!G:G))} -> 2647942 | D4: {=MEDIAN(IF(Multilateral!C:C=A4, Multilateral!F:F))} -> 28897000 | E4: {=MEDIAN(IF(Multilateral!C:C=A4, Multilateral!G:G))} -> 0 | F4: {=MEDIAN(IF(Bonds!C:C=A4, Bonds!E:E))} -> 7044300 | G4: {=MEDIAN(IF('Commercial Banks'!C:C=A4, 'Commercial Banks'!E:E))} -> 19083000 | H4: {=MEDIAN(IF('Other Private'!C:C=A4, 'Other Private'!E:E))} -> 24825426 | I4: {=MEDIAN(IF('IMF Credit'!C:C=A4, 'IMF Credit'!E:E))} -> 0
A5: 1973 | B5: {=MEDIAN(IF(Bilateral!C:C=A5, Bilateral!F:F))} -> 76174968 | C5: {=MEDIAN(IF(Bilateral!C:C=A5,Bilateral!G:G))} -> 4423715 | D5: {=MEDIAN(IF(Multilateral!C:C=A5, Multilateral!F:F))} -> 38308071 | E5: {=MEDIAN(IF(Multilateral!C:C=A5, Multilateral!G:G))} -> 0 | F5: {=MEDIAN(IF(Bonds!C:C=A5, Bonds!E:E))} -> 7161625.6 | G5: {=MEDIAN(IF('Commercial Banks'!C:C=A5, 'Commercial Banks'!E:E))} -> 17755000 | H5: {=MEDIAN(IF('Other Private'!C:C=A5, 'Other Private'!E:E))} -> 25055993 | I5: {=MEDIAN(IF('IMF Credit'!C:C=A5, 'IMF Credit'!E:E))} -> 0
A6: 1974 | B6: {=MEDIAN(IF(Bilateral!C:C=A6, Bilateral!F:F))} -> 93252931 | C6: {=MEDIAN(IF(Bilateral!C:C=A6,Bilateral!G:G))} -> 5289220.5 | D6: {=MEDIAN(IF(Multilateral!C:C=A6, Multilateral!F:F))} -> 47935538 | E6: {=MEDIAN(IF(Multilateral!C:C=A6, Multilateral!G:G))} -> 0 | F6: {=MEDIAN(IF(Bonds!C:C=A6, Bonds!E:E))} -> 7045500 | G6: {=MEDIAN(IF('Commercial Banks'!C:C=A6, 'Commercial Banks'!E:E))} -> 21185170 | H6: {=MEDIAN(IF('Other Private'!C:C=A6, 'Other Private'!E:E))} -> 30908155 | I6: {=MEDIAN(IF('IMF Credit'!C:C=A6, 'IMF Credit'!E:E))} -> 0
A7: 1975 | B7: {=MEDIAN(IF(Bilateral!C:C=A7, Bilateral!F:F))} -> 1.0173819e+08 | C7: {=MEDIAN(IF(Bilateral!C:C=A7,Bilateral!G:G))} -> 14047150 | D7: {=MEDIAN(IF(Multilateral!C:C=A7, Multilateral!F:F))} -> 66387266 | E7: {=MEDIAN(IF(Multilateral!C:C=A7, Multilateral!G:G))} -> 0 | F7: {=MEDIAN(IF(Bonds!C:C=A7, Bonds!E:E))} -> 5877393.6 | G7: {=MEDIAN(IF('Commercial Banks'!C:C=A7, 'Commercial Banks'!E:E))} -> 25061000 | H7: {=MEDIAN(IF('Other Private'!C:C=A7, 'Other Private'!E:E))} -> 33614957 | I7: {=MEDIAN(IF('IMF Credit'!C:C=A7, 'IMF Credit'!E:E))} -> 1439920
A8: 1976 | B8: {=MEDIAN(IF(Bilateral!C:C=A8, Bilateral!F:F))} -> 1.0476371e+08 | C8: {=MEDIAN(IF(Bilateral!C:C=A8,Bilateral!G:G))} -> 29426886 | D8: {=MEDIAN(IF(Multilateral!C:C=A8, Multilateral!F:F))} -> 77184000 | E8: {=MEDIAN(IF(Multilateral!C:C=A8, Multilateral!G:G))} -> 73454.4 | F8: {=MEDIAN(IF(Bonds!C:C=A8, Bonds!E:E))} -> 5992964.6 | G8: {=MEDIAN(IF('Commercial Banks'!C:C=A8, 'Commercial Banks'!E:E))} -> 29599396 | H8: {=MEDIAN(IF('Other Private'!C:C=A8, 'Other Private'!E:E))} -> 36567470 | I8: {=MEDIAN(IF('IMF Credit'!C:C=A8, 'IMF Credit'!E:E))} -> 12437390
A9: 1977 | B9: {=MEDIAN(IF(Bilateral!C:C=A9, Bilateral!F:F))} -> 1.2931173e+08 | C9: {=MEDIAN(IF(Bilateral!C:C=A9,Bilateral!G:G))} -> 37155050 | D9: {=MEDIAN(IF(Multilateral!C:C=A9, Multilateral!F:F))} -> 95986398 | E9: {=MEDIAN(IF(Multilateral!C:C=A9, Multilateral!G:G))} -> 622735.5 | F9: {=MEDIAN(IF(Bonds!C:C=A9, Bonds!E:E))} -> 6529956 | G9: {=MEDIAN(IF('Commercial Banks'!C:C=A9, 'Commercial Banks'!E:E))} -> 58510000 | H9: {=MEDIAN(IF('Other Private'!C:C=A9, 'Other Private'!E:E))} -> 59501002 | I9: {=MEDIAN(IF('IMF Credit'!C:C=A9, 'IMF Credit'!E:E))} -> 13076353
A10: 1978 | B10: {=MEDIAN(IF(Bilateral!C:C=A10, Bilateral!F:F))} -> 1.3507024e+08 | C10: {=MEDIAN(IF(Bilateral!C:C=A10,Bilateral!G:G))} -> 47316750 | D10: {=MEDIAN(IF(Multilateral!C:C=A10, Multilateral!F:F))} -> 1.1782452e+08 | E10: {=MEDIAN(IF(Multilateral!C:C=A10, Multilateral!G:G))} -> 2307745.5 | F10: {=MEDIAN(IF(Bonds!C:C=A10, Bonds!E:E))} -> 9478735.5 | G10: {=MEDIAN(IF('Commercial Banks'!C:C=A10, 'Commercial Banks'!E:E))} -> 69632937 | H10: {=MEDIAN(IF('Other Private'!C:C=A10, 'Other Private'!E:E))} -> 66306948 | I10: {=MEDIAN(IF('IMF Credit'!C:C=A10, 'IMF Credit'!E:E))} -> 19006295
A11: 1979 | B11: {=MEDIAN(IF(Bilateral!C:C=A11, Bilateral!F:F))} -> 1.3735172e+08 | C11: {=MEDIAN(IF(Bilateral!C:C=A11,Bilateral!G:G))} -> 73078000 | D11: {=MEDIAN(IF(Multilateral!C:C=A11, Multilateral!F:F))} -> 137578000 | E11: {=MEDIAN(IF(Multilateral!C:C=A11, Multilateral!G:G))} -> 3368000 | F11: {=MEDIAN(IF(Bonds!C:C=A11, Bonds!E:E))} -> 10638844 | G11: {=MEDIAN(IF('Commercial Banks'!C:C=A11, 'Commercial Banks'!E:E))} -> 1.0582553e+08 | H11: {=MEDIAN(IF('Other Private'!C:C=A11, 'Other Private'!E:E))} -> 1.1959475e+08 | I11: {=MEDIAN(IF('IMF Credit'!C:C=A11, 'IMF Credit'!E:E))} -> 28408221
A12: 1980 | B12: {=MEDIAN(IF(Bilateral!C:C=A12, Bilateral!F:F))} -> 1.5932949e+08 | C12: {=MEDIAN(IF(Bilateral!C:C=A12,Bilateral!G:G))} -> 85827237 | D12: {=MEDIAN(IF(Multilateral!C:C=A12, Multilateral!F:F))} -> 1.7469878e+08 | E12: {=MEDIAN(IF(Multilateral!C:C=A12, Multilateral!G:G))} -> 4553028.6 | F12: {=MEDIAN(IF(Bonds!C:C=A12, Bonds!E:E))} -> 10014239 | G12: {=MEDIAN(IF('Commercial Banks'!C:C=A12, 'Commercial Banks'!E:E))} -> 1.3147414e+08 | H12: {=MEDIAN(IF('Other Private'!C:C=A12, 'Other Private'!E:E))} -> 115486269 | I12: {=MEDIAN(IF('IMF Credit'!C:C=A12, 'IMF Credit'!E:E))} -> 35689983
A13: 1981 | B13: {=MEDIAN(IF(Bilateral!C:C=A13, Bilateral!F:F))} -> 162269000 | C13: {=MEDIAN(IF(Bilateral!C:C=A13,Bilateral!G:G))} -> 76001769 | D13: {=MEDIAN(IF(Multilateral!C:C=A13, Multilateral!F:F))} -> 1.8474878e+08 | E13: {=MEDIAN(IF(Multilateral!C:C=A13, Multilateral!G:G))} -> 4800000 | F13: {=MEDIAN(IF(Bonds!C:C=A13, Bonds!E:E))} -> 8061300 | G13: {=MEDIAN(IF('Commercial Banks'!C:C=A13, 'Commercial Banks'!E:E))} -> 1.4235853e+08 | H13: {=MEDIAN(IF('Other Private'!C:C=A13, 'Other Private'!E:E))} -> 1.3379449e+08 | I13: {=MEDIAN(IF('IMF Credit'!C:C=A13, 'IMF Credit'!E:E))} -> 46546224
A14: 1982 | B14: {=MEDIAN(IF(Bilateral!C:C=A14, Bilateral!F:F))} -> 1.8995256e+08 | C14: {=MEDIAN(IF(Bilateral!C:C=A14,Bilateral!G:G))} -> 72724332 | D14: {=MEDIAN(IF(Multilateral!C:C=A14, Multilateral!F:F))} -> 2.1335933e+08 | E14: {=MEDIAN(IF(Multilateral!C:C=A14, Multilateral!G:G))} -> 6259303.6 | F14: {=MEDIAN(IF(Bonds!C:C=A14, Bonds!E:E))} -> 9049245.3 | G14: {=MEDIAN(IF('Commercial Banks'!C:C=A14, 'Commercial Banks'!E:E))} -> 146358000 | H14: {=MEDIAN(IF('Other Private'!C:C=A14, 'Other Private'!E:E))} -> 1.5541782e+08 | I14: {=MEDIAN(IF('IMF Credit'!C:C=A14, 'IMF Credit'!E:E))} -> 72272066
A15: 1983 | B15: {=MEDIAN(IF(Bilateral!C:C=A15, Bilateral!F:F))} -> 1.8618773e+08 | C15: {=MEDIAN(IF(Bilateral!C:C=A15,Bilateral!G:G))} -> 89622144 | D15: {=MEDIAN(IF(Multilateral!C:C=A15, Multilateral!F:F))} -> 2.545187e+08 | E15: {=MEDIAN(IF(Multilateral!C:C=A15, Multilateral!G:G))} -> 7075435.2 | F15: {=MEDIAN(IF(Bonds!C:C=A15, Bonds!E:E))} -> 20129325 | G15: {=MEDIAN(IF('Commercial Banks'!C:C=A15, 'Commercial Banks'!E:E))} -> 1.5108968e+08 | H15: {=MEDIAN(IF('Other Private'!C:C=A15, 'Other Private'!E:E))} -> 1.4897471e+08 | I15: {=MEDIAN(IF('IMF Credit'!C:C=A15, 'IMF Credit'!E:E))} -> 1.1700752e+08
... A56: 2024 | B56: {=MEDIAN(IF(Bilateral!C:C=A56, Bilateral!F:F))} -> 4.1643617e+08 | C56: {=MEDIAN(IF(Bilateral!C:C=A56,Bilateral!G:G))} -> 6.0269841e+08 | D56: {=MEDIAN(IF(Multilateral!C:C=A56, Multilateral!F:F))} -> 2.6106024e+09 | E56: {=MEDIAN(IF(Multilateral!C:C=A56, Multilateral!G:G))} -> 32695027 | F56: {=MEDIAN(IF(Bonds!C:C=A56, Bonds!E:E))} -> 2651700000 | G56: {=MEDIAN(IF('Commercial Banks'!C:C=A56, 'Commercial Banks'!E:E))} -> 386143000 | H56: {=MEDIAN(IF('Other Private'!C:C=A56, 'Other Private'!E:E))} -> 29730201 | I56: {=MEDIAN(IF('IMF Credit'!C:C=A56, 'IMF Credit'!E:E))} -> 8.4214754e+08

Sheet Resolution_chart
A1: year | B1: Official covered (PC/CF) | C1: Private banks covered (London Club) | D1: Bond debt covered (CACs) | E1: Official outside framework | F1: Private outside framework | G1: Multilateral/IMF outside
A2: 1970 | B2: ='Chart - LIC (median %)'!B2 -> 45.658708 | C2: =IF('Chart - LIC (median %)'!A2>=1976,'Chart - LIC (median %)'!G2,0) -> 0 | D2: =IF('Chart - LIC (median %)'!A2>=2003,'Chart - LIC (median %)'!F2,0) -> 0 | E2: ='Chart - LIC (median %)'!C2 -> 3.251272 | F2: ='Chart - LIC (median %)'!H2 + IF('Chart - LIC (median %)'!A2<1976,'Chart - LIC (median %)'!G2,0) + IF('Chart - LIC (median %)'!A2<2003,'Chart - LIC (median %)'!F2,0) -> 9.789562 | G2: ='Chart - LIC (median %)'!D2+'Chart - LIC (median %)'!E2+'Chart - LIC (median %)'!I2 -> 9.718637 | H2: =SUM(B2:G2) -> 68.418179 | I2: =B2/$H2*100 -> 66.734761 | J2: =C2/$H2*100 -> 0 | K2: =D2/$H2*100 -> 0 | L2: =E2/$H2*100 -> 4.7520586 | M2: =F2/$H2*100 -> 14.308422 | N2: =G2/$H2*100 -> 14.204758
A3: 1971 | B3: ='Chart - LIC (median %)'!B3 -> 44.141864 | C3: =IF('Chart - LIC (median %)'!A3>=1976,'Chart - LIC (median %)'!G3,0) -> 0 | D3: =IF('Chart - LIC (median %)'!A3>=2003,'Chart - LIC (median %)'!F3,0) -> 0 | E3: ='Chart - LIC (median %)'!C3 -> 4.2443129 | F3: ='Chart - LIC (median %)'!H3 + IF('Chart - LIC (median %)'!A3<1976,'Chart - LIC (median %)'!G3,0) + IF('Chart - LIC (median %)'!A3<2003,'Chart - LIC (median %)'!F3,0) -> 8.9706429 | G3: ='Chart - LIC (median %)'!D3+'Chart - LIC (median %)'!E3+'Chart - LIC (median %)'!I3 -> 10.83325 | H3: =SUM(B3:G3) -> 68.190069 | I3: =B3/$H3*100 -> 64.733566 | J3: =C3/$H3*100 -> 0 | K3: =D3/$H3*100 -> 0 | L3: =E3/$H3*100 -> 6.224239 | M3: =F3/$H3*100 -> 13.155351 | N3: =G3/$H3*100 -> 15.886844
A4: 1972 | B4: ='Chart - LIC (median %)'!B4 -> 39.405158 | C4: =IF('Chart - LIC (median %)'!A4>=1976,'Chart - LIC (median %)'!G4,0) -> 0 | D4: =IF('Chart - LIC (median %)'!A4>=2003,'Chart - LIC (median %)'!F4,0) -> 0 | E4: ='Chart - LIC (median %)'!C4 -> 4.9758693 | F4: ='Chart - LIC (median %)'!H4 + IF('Chart - LIC (median %)'!A4<1976,'Chart - LIC (median %)'!G4,0) + IF('Chart - LIC (median %)'!A4<2003,'Chart - LIC (median %)'!F4,0) -> 7.6960497 | G4: ='Chart - LIC (median %)'!D4+'Chart - LIC (median %)'!E4+'Chart - LIC (median %)'!I4 -> 15.068458 | H4: =SUM(B4:G4) -> 67.145536 | I4: =B4/$H4*100 -> 58.686192 | J4: =C4/$H4*100 -> 0 | K4: =D4/$H4*100 -> 0 | L4: =E4/$H4*100 -> 7.4105736 | M4: =F4/$H4*100 -> 11.461744 | N4: =G4/$H4*100 -> 22.44149
A5: 1973 | B5: ='Chart - LIC (median %)'!B5 -> 30.578687 | C5: =IF('Chart - LIC (median %)'!A5>=1976,'Chart - LIC (median %)'!G5,0) -> 0 | D5: =IF('Chart - LIC (median %)'!A5>=2003,'Chart - LIC (median %)'!F5,0) -> 0 | E5: ='Chart - LIC (median %)'!C5 -> 5.1044962 | F5: ='Chart - LIC (median %)'!H5 + IF('Chart - LIC (median %)'!A5<1976,'Chart - LIC (median %)'!G5,0) + IF('Chart - LIC (median %)'!A5<2003,'Chart - LIC (median %)'!F5,0) -> 7.707648 | G5: ='Chart - LIC (median %)'!D5+'Chart - LIC (median %)'!E5+'Chart - LIC (median %)'!I5 -> 12.996006 | H5: =SUM(B5:G5) -> 56.386838 | I5: =B5/$H5*100 -> 54.230186 | J5: =C5/$H5*100 -> 0 | K5: =D5/$H5*100 -> 0 | L5: =E5/$H5*100 -> 9.0526377 | M5: =F5/$H5*100 -> 13.669233 | N5: =G5/$H5*100 -> 23.047943
A6: 1974 | B6: ='Chart - LIC (median %)'!B6 -> 31.229706 | C6: =IF('Chart - LIC (median %)'!A6>=1976,'Chart - LIC (median %)'!G6,0) -> 0 | D6: =IF('Chart - LIC (median %)'!A6>=2003,'Chart - LIC (median %)'!F6,0) -> 0 | E6: ='Chart - LIC (median %)'!C6 -> 5.0073772 | F6: ='Chart - LIC (median %)'!H6 + IF('Chart - LIC (median %)'!A6<1976,'Chart - LIC (median %)'!G6,0) + IF('Chart - LIC (median %)'!A6<2003,'Chart - LIC (median %)'!F6,0) -> 9.6494524 | G6: ='Chart - LIC (median %)'!D6+'Chart - LIC (median %)'!E6+'Chart - LIC (median %)'!I6 -> 14.552288 | H6: =SUM(B6:G6) -> 60.438824 | I6: =B6/$H6*100 -> 51.671598 | J6: =C6/$H6*100 -> 0 | K6: =D6/$H6*100 -> 0 | L6: =E6/$H6*100 -> 8.2850342 | M6: =F6/$H6*100 -> 15.965652 | N6: =G6/$H6*100 -> 24.077716
A7: 1975 | B7: ='Chart - LIC (median %)'!B7 -> 28.876345 | C7: =IF('Chart - LIC (median %)'!A7>=1976,'Chart - LIC (median %)'!G7,0) -> 0 | D7: =IF('Chart - LIC (median %)'!A7>=2003,'Chart - LIC (median %)'!F7,0) -> 0 | E7: ='Chart - LIC (median %)'!C7 -> 7.1529057 | F7: ='Chart - LIC (median %)'!H7 + IF('Chart - LIC (median %)'!A7<1976,'Chart - LIC (median %)'!G7,0) + IF('Chart - LIC (median %)'!A7<2003,'Chart - LIC (median %)'!F7,0) -> 8.1675217 | G7: ='Chart - LIC (median %)'!D7+'Chart - LIC (median %)'!E7+'Chart - LIC (median %)'!I7 -> 17.79386 | H7: =SUM(B7:G7) -> 61.990632 | I7: =B7/$H7*100 -> 46.581788 | J7: =C7/$H7*100 -> 0 | K7: =D7/$H7*100 -> 0 | L7: =E7/$H7*100 -> 11.538688 | M7: =F7/$H7*100 -> 13.175413 | N7: =G7/$H7*100 -> 28.704111
A8: 1976 | B8: ='Chart - LIC (median %)'!B8 -> 25.565587 | C8: =IF('Chart - LIC (median %)'!A8>=1976,'Chart - LIC (median %)'!G8,0) -> 0.22229976 | D8: =IF('Chart - LIC (median %)'!A8>=2003,'Chart - LIC (median %)'!F8,0) -> 0 | E8: ='Chart - LIC (median %)'!C8 -> 12.256348 | F8: ='Chart - LIC (median %)'!H8 + IF('Chart - LIC (median %)'!A8<1976,'Chart - LIC (median %)'!G8,0) + IF('Chart - LIC (median %)'!A8<2003,'Chart - LIC (median %)'!F8,0) -> 6.890248 | G8: ='Chart - LIC (median %)'!D8+'Chart - LIC (median %)'!E8+'Chart - LIC (median %)'!I8 -> 23.627186 | H8: =SUM(B8:G8) -> 68.561669 | I8: =B8/$H8*100 -> 37.288454 | J8: =C8/$H8*100 -> 0.3242333 | K8: =D8/$H8*100 -> 0 | L8: =E8/$H8*100 -> 17.876385 | M8: =F8/$H8*100 -> 10.049709 | N8: =G8/$H8*100 -> 34.461218
A9: 1977 | B9: ='Chart - LIC (median %)'!B9 -> 21.339671 | C9: =IF('Chart - LIC (median %)'!A9>=1976,'Chart - LIC (median %)'!G9,0) -> 0.2549168 | D9: =IF('Chart - LIC (median %)'!A9>=2003,'Chart - LIC (median %)'!F9,0) -> 0 | E9: ='Chart - LIC (median %)'!C9 -> 11.022876 | F9: ='Chart - LIC (median %)'!H9 + IF('Chart - LIC (median %)'!A9<1976,'Chart - LIC (median %)'!G9,0) + IF('Chart - LIC (median %)'!A9<2003,'Chart - LIC (median %)'!F9,0) -> 7.9252355 | G9: ='Chart - LIC (median %)'!D9+'Chart - LIC (median %)'!E9+'Chart - LIC (median %)'!I9 -> 23.828469 | H9: =SUM(B9:G9) -> 64.371169 | I9: =B9/$H9*100 -> 33.150977 | J9: =C9/$H9*100 -> 0.39601083 | K9: =D9/$H9*100 -> 0 | L9: =E9/$H9*100 -> 17.123933 | M9: =F9/$H9*100 -> 12.311778 | N9: =G9/$H9*100 -> 37.017301
A10: 1978 | B10: ='Chart - LIC (median %)'!B10 -> 19.085527 | C10: =IF('Chart - LIC (median %)'!A10>=1976,'Chart - LIC (median %)'!G10,0) -> 0.65883195 | D10: =IF('Chart - LIC (median %)'!A10>=2003,'Chart - LIC (median %)'!F10,0) -> 0 | E10: ='Chart - LIC (median %)'!C10 -> 10.842735 | F10: ='Chart - LIC (median %)'!H10 + IF('Chart - LIC (median %)'!A10<1976,'Chart - LIC (median %)'!G10,0) + IF('Chart - LIC (median %)'!A10<2003,'Chart - LIC (median %)'!F10,0) -> 8.5682422 | G10: ='Chart - LIC (median %)'!D10+'Chart - LIC (median %)'!E10+'Chart - LIC (median %)'!I10 -> 24.969724 | H10: =SUM(B10:G10) -> 64.12506 | I10: =B10/$H10*100 -> 29.762978 | J10: =C10/$H10*100 -> 1.0274173 | K10: =D10/$H10*100 -> 0 | L10: =E10/$H10*100 -> 16.908733 | M10: =F10/$H10*100 -> 13.361769 | N10: =G10/$H10*100 -> 38.939104
A11: 1979 | B11: ='Chart - LIC (median %)'!B11 -> 18.147896 | C11: =IF('Chart - LIC (median %)'!A11>=1976,'Chart - LIC (median %)'!G11,0) -> 1.4709424 | D11: =IF('Chart - LIC (median %)'!A11>=2003,'Chart - LIC (median %)'!F11,0) -> 0 | E11: ='Chart - LIC (median %)'!C11 -> 13.592922 | F11: ='Chart - LIC (median %)'!H11 + IF('Chart - LIC (median %)'!A11<1976,'Chart - LIC (median %)'!G11,0) + IF('Chart - LIC (median %)'!A11<2003,'Chart - LIC (median %)'!F11,0) -> 6.4913426 | G11: ='Chart - LIC (median %)'!D11+'Chart - LIC (median %)'!E11+'Chart - LIC (median %)'!I11 -> 27.11958 | H11: =SUM(B11:G11) -> 66.822683 | I11: =B11/$H11*100 -> 27.158286 | J11: =C11/$H11*100 -> 2.2012621 | K11: =D11/$H11*100 -> 0 | L11: =E11/$H11*100 -> 20.341779 | M11: =F11/$H11*100 -> 9.7142801 | N11: =G11/$H11*100 -> 40.584393
A12: 1980 | B12: ='Chart - LIC (median %)'!B12 -> 16.803068 | C12: =IF('Chart - LIC (median %)'!A12>=1976,'Chart - LIC (median %)'!G12,0) -> 2.0838489 | D12: =IF('Chart - LIC (median %)'!A12>=2003,'Chart - LIC (median %)'!F12,0) -> 0 | E12: ='Chart - LIC (median %)'!C12 -> 11.966859 | F12: ='Chart - LIC (median %)'!H12 + IF('Chart - LIC (median %)'!A12<1976,'Chart - LIC (median %)'!G12,0) + IF('Chart - LIC (median %)'!A12<2003,'Chart - LIC (median %)'!F12,0) -> 6.5044917 | G12: ='Chart - LIC (median %)'!D12+'Chart - LIC (median %)'!E12+'Chart - LIC (median %)'!I12 -> 29.272788 | H12: =SUM(B12:G12) -> 66.631055 | I12: =B12/$H12*100 -> 25.218072 | J12: =C12/$H12*100 -> 3.127444 | K12: =D12/$H12*100 -> 0 | L12: =E12/$H12*100 -> 17.959882 | M12: =F12/$H12*100 -> 9.7619521 | N12: =G12/$H12*100 -> 43.93265
A13: 1981 | B13: ='Chart - LIC (median %)'!B13 -> 13.778048 | C13: =IF('Chart - LIC (median %)'!A13>=1976,'Chart - LIC (median %)'!G13,0) -> 1.7272914 | D13: =IF('Chart - LIC (median %)'!A13>=2003,'Chart - LIC (median %)'!F13,0) -> 0 | E13: ='Chart - LIC (median %)'!C13 -> 13.870036 | F13: ='Chart - LIC (median %)'!H13 + IF('Chart - LIC (median %)'!A13<1976,'Chart - LIC (median %)'!G13,0) + IF('Chart - LIC (median %)'!A13<2003,'Chart - LIC (median %)'!F13,0) -> 6.962448 | G13: ='Chart - LIC (median %)'!D13+'Chart - LIC (median %)'!E13+'Chart - LIC (median %)'!I13 -> 31.992837 | H13: =SUM(B13:G13) -> 68.33066 | I13: =B13/$H13*100 -> 20.163786 | J13: =C13/$H13*100 -> 2.5278423 | K13: =D13/$H13*100 -> 0 | L13: =E13/$H13*100 -> 20.298407 | M13: =F13/$H13*100 -> 10.189347 | N13: =G13/$H13*100 -> 46.820618
... A56: 2024 | B56: ='Chart - LIC (median %)'!B56 -> 4.5226523 | C56: =IF('Chart - LIC (median %)'!A56>=1976,'Chart - LIC (median %)'!G56,0) -> 1.0526253 | D56: =IF('Chart - LIC (median %)'!A56>=2003,'Chart - LIC (median %)'!F56,0) -> 0 | E56: ='Chart - LIC (median %)'!C56 -> 18.674166 | F56: ='Chart - LIC (median %)'!H56 + IF('Chart - LIC (median %)'!A56<1976,'Chart - LIC (median %)'!G56,0) + IF('Chart - LIC (median %)'!A56<2003,'Chart - LIC (median %)'!F56,0) -> 0 | G56: ='Chart - LIC (median %)'!D56+'Chart - LIC (median %)'!E56+'Chart - LIC (median %)'!I56 -> 54.002689 | H56: =SUM(B56:G56) -> 78.252133 | I56: =B56/$H56*100 -> 5.7795898 | J56: =C56/$H56*100 -> 1.3451714 | K56: =D56/$H56*100 -> 0 | L56: =E56/$H56*100 -> 23.864099 | M56: =F56/$H56*100 -> 0 | N56: =G56/$H56*100 -> 69.01114

Sheet Chart - MIC (median %)
A1: year | B1: pct_Bilateral_PC | C1: pct_Bilateral_NonPC | D1: pct_Multilateral_PCS | E1: pct_Multilateral_NonPCS | F1: pct_Bonds | G1: pct_Commercial_Banks | H1: pct_Other_Private | I1: pct_IMF
A2: 1970 | B2: 39.426986 | C2: 0.70256619 | D2: 18.642886 | E2: 0 | F2: 1.5007103 | G2: 1.3795184 | H2: 9.4878427 | I2: 0
A3: 1971 | B3: 38.195436 | C3: 1.3985949 | D3: 18.508252 | E3: 0 | F3: 1.2785917 | G3: 1.442687 | H3: 10.009514 | I3: 0
A4: 1972 | B4: 38.598868 | C4: 1.2694261 | D4: 18.909792 | E4: 0 | F4: 1.0231522 | G4: 4.7484 | H4: 9.5729571 | I4: 0
A5: 1973 | B5: 40.502721 | C5: 1.2309151 | D5: 17.46827 | E5: 0 | F5: 0.92529871 | G5: 4.5585908 | H5: 7.9687709 | I5: 0
A6: 1974 | B6: 38.507651 | C6: 2.0708255 | D6: 18.475274 | E6: 0 | F6: 1.2276935 | G6: 5.8782738 | H6: 8.2978839 | I6: 0
A7: 1975 | B7: 32.246778 | C7: 5.9729732 | D7: 19.640962 | E7: 0 | F7: 0.64571606 | G7: 7.9334326 | H7: 9.1364398 | I7: 0
A8: 1976 | B8: 28.025952 | C8: 6.3890978 | D8: 17.973992 | E8: 0 | F8: 0.72298413 | G8: 9.3623032 | H8: 7.4206747 | I8: 0.0013987269
A9: 1977 | B9: 28.194223 | C9: 7.2037087 | D9: 17.222351 | E9: 0 | F9: 0.39003445 | G9: 10.841721 | H9: 6.1930398 | I9: 1.2742692
A10: 1978 | B10: 25.588308 | C10: 8.9961939 | D10: 17.200892 | E10: 0.08036584 | F10: 0.88492356 | G10: 17.641635 | H10: 5.7325242 | I10: 0.95622405
A11: 1979 | B11: 24.002037 | C11: 9.0515487 | D11: 16.3934 | E11: 0.16697102 | F11: 0.5893946 | G11: 23.052881 | H11: 6.3979048 | I11: 1.1945812
A12: 1980 | B12: 21.998613 | C12: 8.3593203 | D12: 16.643823 | E12: 0.15949885 | F12: 0.30934428 | G12: 22.840859 | H12: 7.1149783 | I12: 1.1275335
A13: 1981 | B13: 19.97043 | C13: 6.9150929 | D13: 17.120311 | E13: 0.19921484 | F13: 0.13884641 | G13: 18.057582 | H13: 8.1310313 | I13: 1.5318611
... A56: 2024 | B56: 5.3019061 | C56: 3.5968048 | D56: 26.651772 | E56: 0.41849306 | F56: 25.299271 | G56: 2.7498712 | H56: 0 | I56: 8.5899424

Sheet PC Members
A1: ca_code | B1: pc_name | C1: accession_year
A2: 801 | B2: Australia | C2: 1956
A3: 001 | B3: Austria | C3: 1956
A4: 002 | B4: Belgium | C4: 1956
A5: 301 | B5: Canada | C5: 1956
A6: 003 | B6: Denmark | C6: 1956
A7: 018 | B7: Finland | C7: 1956
A8: 004 | B8: France | C8: 1956
A9: 005 | B9: Germany, Fed. Rep. | C9: 1956
A10: 021 | B10: Ireland | C10: 1956
A11: 006 | B11: Italy | C11: 1956
A12: 701 | B12: Japan | C12: 1956
A13: 007 | B13: Netherlands | C13: 1956
... A23: 431 | B23: Brazil | C23: 2016

Sheet PCS Institutions
A1: ca_code | B1: ca_name
A2: 913 | B2: African Dev. Bank
A3: 953 | B3: Arab Bank for Economic Dev. in Africa (BADEA)
A4: 973 | B4: Arab Monetary Fund
A5: 915 | B5: Asian Dev. Bank
A6: 899 | B6: Asian Infrastructure Investment Bank
A7: 911 | B7: Bank for International Settlements (BIS)
A8: 906 | B8: Caribbean Dev. Bank
A9: 920 | B9: Corporacion Andina de Fomento
A10: 926 | B10: Council of Europe
A11: 990 | B11: European Bank for Reconstruction and Dev. (EBRD)
A12: 919 | B12: European Investment Bank
... A22: 902 | B22: World Bank-MIGA
